calculadorafabeliz/__init__.py
calculadorafabeliz/basicOperations.py
calculadorafabeliz/mathOperations.py
calculadora_fabeliz-1.5.3.dist-info/LICENSE
calculadora_fabeliz-1.5.3.dist-info/METADATA
calculadora_fabeliz-1.5.3.dist-info/WHEEL
calculadora_fabeliz-1.5.3.dist-info/top_level.txt
calculadora_fabeliz-1.5.3.dist-info/RECORD
