Metadata-Version: 2.1
Name: calculadora-fabeliz
Version: 1.5.3
Summary: Calculadora Matematica / Math Calculator
Author: Fabeliz Irene Alvarez Salazar
Author-email: irenex2018@gmail.com
License-File: LICENSE
